mlflow_torchserve/__init__.py
mlflow_torchserve/config.py
tests/__init__.py
tests/conftest.py
tests/test_cli.py
tests/test_plugin.py
tests/resources/__init__.py
tests/resources/linear_handler.py
tests/resources/linear_model.py
mlflow_torchserve-0.1.0.dist-info/LICENSE.txt
mlflow_torchserve-0.1.0.dist-info/METADATA
mlflow_torchserve-0.1.0.dist-info/WHEEL
mlflow_torchserve-0.1.0.dist-info/entry_points.txt
mlflow_torchserve-0.1.0.dist-info/top_level.txt
mlflow_torchserve-0.1.0.dist-info/RECORD
