Metadata-Version: 2.1
Name: mlflow-torchserve
Version: 0.1.0
Summary: Torch Serve Mlflow Deployment
Home-page: UNKNOWN
Author: UNKNOWN
Author-email: UNKNOWN
License: UNKNOWN
Platform: UNKNOWN
Requires-Dist: mlflow (>=1.12.0)
Requires-Dist: torchserve
Requires-Dist: torch-model-archiver
